{"frames": [

{
	"filename": "duck001.png",
	"frame": {"x":2,"y":2,"w":400,"h":400},
	"rotated": false,
	"trimmed": false,
	"spriteSourceSize": {"x":0,"y":0,"w":400,"h":400},
	"sourceSize": {"w":400,"h":400}
},
{
	"filename": "duck002.png",
	"frame": {"x":404,"y":2,"w":400,"h":400},
	"rotated": false,
	"trimmed": false,
	"spriteSourceSize": {"x":0,"y":0,"w":400,"h":400},
	"sourceSize": {"w":400,"h":400}
},
{
	"filename": "duck003.png",
	"frame": {"x":806,"y":2,"w":400,"h":400},
	"rotated": false,
	"trimmed": false,
	"spriteSourceSize": {"x":0,"y":0,"w":400,"h":400},
	"sourceSize": {"w":400,"h":400}
},
{
	"filename": "duck004.png",
	"frame": {"x":1208,"y":2,"w":400,"h":400},
	"rotated": false,
	"trimmed": false,
	"spriteSourceSize": {"x":0,"y":0,"w":400,"h":400},
	"sourceSize": {"w":400,"h":400}
},
{
	"filename": "duck005.png",
	"frame": {"x":1610,"y":2,"w":400,"h":400},
	"rotated": false,
	"trimmed": false,
	"spriteSourceSize": {"x":0,"y":0,"w":400,"h":400},
	"sourceSize": {"w":400,"h":400}
},
{
	"filename": "duck006.png",
	"frame": {"x":2012,"y":2,"w":400,"h":400},
	"rotated": false,
	"trimmed": false,
	"spriteSourceSize": {"x":0,"y":0,"w":400,"h":400},
	"sourceSize": {"w":400,"h":400}
},
{
	"filename": "duck007.png",
	"frame": {"x":2,"y":404,"w":400,"h":400},
	"rotated": false,
	"trimmed": false,
	"spriteSourceSize": {"x":0,"y":0,"w":400,"h":400},
	"sourceSize": {"w":400,"h":400}
},
{
	"filename": "duck008.png",
	"frame": {"x":404,"y":404,"w":400,"h":400},
	"rotated": false,
	"trimmed": false,
	"spriteSourceSize": {"x":0,"y":0,"w":400,"h":400},
	"sourceSize": {"w":400,"h":400}
},
{
	"filename": "duck009.png",
	"frame": {"x":806,"y":404,"w":400,"h":400},
	"rotated": false,
	"trimmed": false,
	"spriteSourceSize": {"x":0,"y":0,"w":400,"h":400},
	"sourceSize": {"w":400,"h":400}
},
{
	"filename": "duck010.png",
	"frame": {"x":1208,"y":404,"w":400,"h":400},
	"rotated": false,
	"trimmed": false,
	"spriteSourceSize": {"x":0,"y":0,"w":400,"h":400},
	"sourceSize": {"w":400,"h":400}
},
{
	"filename": "duck011.png",
	"frame": {"x":1610,"y":404,"w":400,"h":400},
	"rotated": false,
	"trimmed": false,
	"spriteSourceSize": {"x":0,"y":0,"w":400,"h":400},
	"sourceSize": {"w":400,"h":400}
},
{
	"filename": "duck012.png",
	"frame": {"x":2012,"y":404,"w":400,"h":400},
	"rotated": false,
	"trimmed": false,
	"spriteSourceSize": {"x":0,"y":0,"w":400,"h":400},
	"sourceSize": {"w":400,"h":400}
},
{
	"filename": "duck013.png",
	"frame": {"x":2,"y":806,"w":400,"h":400},
	"rotated": false,
	"trimmed": false,
	"spriteSourceSize": {"x":0,"y":0,"w":400,"h":400},
	"sourceSize": {"w":400,"h":400}
},
{
	"filename": "duck014.png",
	"frame": {"x":404,"y":806,"w":400,"h":400},
	"rotated": false,
	"trimmed": false,
	"spriteSourceSize": {"x":0,"y":0,"w":400,"h":400},
	"sourceSize": {"w":400,"h":400}
},
{
	"filename": "duck015.png",
	"frame": {"x":806,"y":806,"w":400,"h":400},
	"rotated": false,
	"trimmed": false,
	"spriteSourceSize": {"x":0,"y":0,"w":400,"h":400},
	"sourceSize": {"w":400,"h":400}
},
{
	"filename": "duck016.png",
	"frame": {"x":1208,"y":806,"w":400,"h":400},
	"rotated": false,
	"trimmed": false,
	"spriteSourceSize": {"x":0,"y":0,"w":400,"h":400},
	"sourceSize": {"w":400,"h":400}
},
{
	"filename": "duck017.png",
	"frame": {"x":1610,"y":806,"w":400,"h":400},
	"rotated": false,
	"trimmed": false,
	"spriteSourceSize": {"x":0,"y":0,"w":400,"h":400},
	"sourceSize": {"w":400,"h":400}
},
{
	"filename": "duck018.png",
	"frame": {"x":2012,"y":806,"w":400,"h":400},
	"rotated": false,
	"trimmed": false,
	"spriteSourceSize": {"x":0,"y":0,"w":400,"h":400},
	"sourceSize": {"w":400,"h":400}
},
{
	"filename": "duckwalk001.png",
	"frame": {"x":2,"y":1208,"w":400,"h":400},
	"rotated": false,
	"trimmed": false,
	"spriteSourceSize": {"x":0,"y":0,"w":400,"h":400},
	"sourceSize": {"w":400,"h":400}
},
{
	"filename": "duckwalk002.png",
	"frame": {"x":404,"y":1208,"w":400,"h":400},
	"rotated": false,
	"trimmed": false,
	"spriteSourceSize": {"x":0,"y":0,"w":400,"h":400},
	"sourceSize": {"w":400,"h":400}
},
{
	"filename": "duckwalk003.png",
	"frame": {"x":806,"y":1208,"w":400,"h":400},
	"rotated": false,
	"trimmed": false,
	"spriteSourceSize": {"x":0,"y":0,"w":400,"h":400},
	"sourceSize": {"w":400,"h":400}
},
{
	"filename": "duckwalk004.png",
	"frame": {"x":1208,"y":1208,"w":400,"h":400},
	"rotated": false,
	"trimmed": false,
	"spriteSourceSize": {"x":0,"y":0,"w":400,"h":400},
	"sourceSize": {"w":400,"h":400}
},
{
	"filename": "duckwalk005.png",
	"frame": {"x":1610,"y":1208,"w":400,"h":400},
	"rotated": false,
	"trimmed": false,
	"spriteSourceSize": {"x":0,"y":0,"w":400,"h":400},
	"sourceSize": {"w":400,"h":400}
},
{
	"filename": "duckwalk006.png",
	"frame": {"x":2012,"y":1208,"w":400,"h":400},
	"rotated": false,
	"trimmed": false,
	"spriteSourceSize": {"x":0,"y":0,"w":400,"h":400},
	"sourceSize": {"w":400,"h":400}
},
{
	"filename": "duckwalk007.png",
	"frame": {"x":2,"y":1610,"w":400,"h":400},
	"rotated": false,
	"trimmed": false,
	"spriteSourceSize": {"x":0,"y":0,"w":400,"h":400},
	"sourceSize": {"w":400,"h":400}
},
{
	"filename": "duckwalkturn001.png",
	"frame": {"x":404,"y":1610,"w":400,"h":400},
	"rotated": false,
	"trimmed": false,
	"spriteSourceSize": {"x":0,"y":0,"w":400,"h":400},
	"sourceSize": {"w":400,"h":400}
},
{
	"filename": "encounteredge.png",
	"frame": {"x":806,"y":1610,"w":400,"h":400},
	"rotated": false,
	"trimmed": false,
	"spriteSourceSize": {"x":0,"y":0,"w":400,"h":400},
	"sourceSize": {"w":400,"h":400}
},
{
	"filename": "encountersteepangle.png",
	"frame": {"x":1208,"y":1610,"w":400,"h":400},
	"rotated": false,
	"trimmed": false,
	"spriteSourceSize": {"x":0,"y":0,"w":400,"h":400},
	"sourceSize": {"w":400,"h":400}
},
{
	"filename": "fallimpact.png",
	"frame": {"x":1610,"y":1610,"w":400,"h":400},
	"rotated": false,
	"trimmed": false,
	"spriteSourceSize": {"x":0,"y":0,"w":400,"h":400},
	"sourceSize": {"w":400,"h":400}
},
{
	"filename": "falling001.png",
	"frame": {"x":2012,"y":1610,"w":400,"h":400},
	"rotated": false,
	"trimmed": false,
	"spriteSourceSize": {"x":0,"y":0,"w":400,"h":400},
	"sourceSize": {"w":400,"h":400}
},
{
	"filename": "falling002.png",
	"frame": {"x":2,"y":2012,"w":400,"h":400},
	"rotated": false,
	"trimmed": false,
	"spriteSourceSize": {"x":0,"y":0,"w":400,"h":400},
	"sourceSize": {"w":400,"h":400}
},
{
	"filename": "falling003.png",
	"frame": {"x":404,"y":2012,"w":400,"h":400},
	"rotated": false,
	"trimmed": false,
	"spriteSourceSize": {"x":0,"y":0,"w":400,"h":400},
	"sourceSize": {"w":400,"h":400}
},
{
	"filename": "falling004.png",
	"frame": {"x":806,"y":2012,"w":400,"h":400},
	"rotated": false,
	"trimmed": false,
	"spriteSourceSize": {"x":0,"y":0,"w":400,"h":400},
	"sourceSize": {"w":400,"h":400}
},
{
	"filename": "falling005.png",
	"frame": {"x":1208,"y":2012,"w":400,"h":400},
	"rotated": false,
	"trimmed": false,
	"spriteSourceSize": {"x":0,"y":0,"w":400,"h":400},
	"sourceSize": {"w":400,"h":400}
},
{
	"filename": "falling006.png",
	"frame": {"x":1610,"y":2012,"w":400,"h":400},
	"rotated": false,
	"trimmed": false,
	"spriteSourceSize": {"x":0,"y":0,"w":400,"h":400},
	"sourceSize": {"w":400,"h":400}
},
{
	"filename": "falling007.png",
	"frame": {"x":2012,"y":2012,"w":400,"h":400},
	"rotated": false,
	"trimmed": false,
	"spriteSourceSize": {"x":0,"y":0,"w":400,"h":400},
	"sourceSize": {"w":400,"h":400}
},
{
	"filename": "idle001.png",
	"frame": {"x":2,"y":2414,"w":400,"h":400},
	"rotated": false,
	"trimmed": false,
	"spriteSourceSize": {"x":0,"y":0,"w":400,"h":400},
	"sourceSize": {"w":400,"h":400}
},
{
	"filename": "idle002.png",
	"frame": {"x":404,"y":2414,"w":400,"h":400},
	"rotated": false,
	"trimmed": false,
	"spriteSourceSize": {"x":0,"y":0,"w":400,"h":400},
	"sourceSize": {"w":400,"h":400}
},
{
	"filename": "idle003.png",
	"frame": {"x":806,"y":2414,"w":400,"h":400},
	"rotated": false,
	"trimmed": false,
	"spriteSourceSize": {"x":0,"y":0,"w":400,"h":400},
	"sourceSize": {"w":400,"h":400}
},
{
	"filename": "idle004.png",
	"frame": {"x":1208,"y":2414,"w":400,"h":400},
	"rotated": false,
	"trimmed": false,
	"spriteSourceSize": {"x":0,"y":0,"w":400,"h":400},
	"sourceSize": {"w":400,"h":400}
},
{
	"filename": "idle005.png",
	"frame": {"x":1610,"y":2414,"w":400,"h":400},
	"rotated": false,
	"trimmed": false,
	"spriteSourceSize": {"x":0,"y":0,"w":400,"h":400},
	"sourceSize": {"w":400,"h":400}
},
{
	"filename": "idle006.png",
	"frame": {"x":2012,"y":2414,"w":400,"h":400},
	"rotated": false,
	"trimmed": false,
	"spriteSourceSize": {"x":0,"y":0,"w":400,"h":400},
	"sourceSize": {"w":400,"h":400}
},
{
	"filename": "turn001.png",
	"frame": {"x":2,"y":2816,"w":400,"h":400},
	"rotated": false,
	"trimmed": false,
	"spriteSourceSize": {"x":0,"y":0,"w":400,"h":400},
	"sourceSize": {"w":400,"h":400}
},
{
	"filename": "turn002.png",
	"frame": {"x":404,"y":2816,"w":400,"h":400},
	"rotated": false,
	"trimmed": false,
	"spriteSourceSize": {"x":0,"y":0,"w":400,"h":400},
	"sourceSize": {"w":400,"h":400}
},
{
	"filename": "turn003.png",
	"frame": {"x":806,"y":2816,"w":400,"h":400},
	"rotated": false,
	"trimmed": false,
	"spriteSourceSize": {"x":0,"y":0,"w":400,"h":400},
	"sourceSize": {"w":400,"h":400}
},
{
	"filename": "turn004.png",
	"frame": {"x":1208,"y":2816,"w":400,"h":400},
	"rotated": false,
	"trimmed": false,
	"spriteSourceSize": {"x":0,"y":0,"w":400,"h":400},
	"sourceSize": {"w":400,"h":400}
},
{
	"filename": "unduck001.png",
	"frame": {"x":1610,"y":2816,"w":400,"h":400},
	"rotated": false,
	"trimmed": false,
	"spriteSourceSize": {"x":0,"y":0,"w":400,"h":400},
	"sourceSize": {"w":400,"h":400}
},
{
	"filename": "unduck002.png",
	"frame": {"x":2012,"y":2816,"w":400,"h":400},
	"rotated": false,
	"trimmed": false,
	"spriteSourceSize": {"x":0,"y":0,"w":400,"h":400},
	"sourceSize": {"w":400,"h":400}
},
{
	"filename": "unduck003.png",
	"frame": {"x":2,"y":3218,"w":400,"h":400},
	"rotated": false,
	"trimmed": false,
	"spriteSourceSize": {"x":0,"y":0,"w":400,"h":400},
	"sourceSize": {"w":400,"h":400}
},
{
	"filename": "unduck004.png",
	"frame": {"x":404,"y":3218,"w":400,"h":400},
	"rotated": false,
	"trimmed": false,
	"spriteSourceSize": {"x":0,"y":0,"w":400,"h":400},
	"sourceSize": {"w":400,"h":400}
},
{
	"filename": "unduck005.png",
	"frame": {"x":806,"y":3218,"w":400,"h":400},
	"rotated": false,
	"trimmed": false,
	"spriteSourceSize": {"x":0,"y":0,"w":400,"h":400},
	"sourceSize": {"w":400,"h":400}
},
{
	"filename": "unduck006.png",
	"frame": {"x":1208,"y":3218,"w":400,"h":400},
	"rotated": false,
	"trimmed": false,
	"spriteSourceSize": {"x":0,"y":0,"w":400,"h":400},
	"sourceSize": {"w":400,"h":400}
},
{
	"filename": "unduck007.png",
	"frame": {"x":1610,"y":3218,"w":400,"h":400},
	"rotated": false,
	"trimmed": false,
	"spriteSourceSize": {"x":0,"y":0,"w":400,"h":400},
	"sourceSize": {"w":400,"h":400}
},
{
	"filename": "unduck008.png",
	"frame": {"x":2012,"y":3218,"w":400,"h":400},
	"rotated": false,
	"trimmed": false,
	"spriteSourceSize": {"x":0,"y":0,"w":400,"h":400},
	"sourceSize": {"w":400,"h":400}
},
{
	"filename": "unduck009.png",
	"frame": {"x":2,"y":3620,"w":400,"h":400},
	"rotated": false,
	"trimmed": false,
	"spriteSourceSize": {"x":0,"y":0,"w":400,"h":400},
	"sourceSize": {"w":400,"h":400}
},
{
	"filename": "unduck010.png",
	"frame": {"x":404,"y":3620,"w":400,"h":400},
	"rotated": false,
	"trimmed": false,
	"spriteSourceSize": {"x":0,"y":0,"w":400,"h":400},
	"sourceSize": {"w":400,"h":400}
},
{
	"filename": "unduck011.png",
	"frame": {"x":806,"y":3620,"w":400,"h":400},
	"rotated": false,
	"trimmed": false,
	"spriteSourceSize": {"x":0,"y":0,"w":400,"h":400},
	"sourceSize": {"w":400,"h":400}
},
{
	"filename": "walk001.png",
	"frame": {"x":1208,"y":3620,"w":400,"h":400},
	"rotated": false,
	"trimmed": false,
	"spriteSourceSize": {"x":0,"y":0,"w":400,"h":400},
	"sourceSize": {"w":400,"h":400}
},
{
	"filename": "walk002.png",
	"frame": {"x":1610,"y":3620,"w":400,"h":400},
	"rotated": false,
	"trimmed": false,
	"spriteSourceSize": {"x":0,"y":0,"w":400,"h":400},
	"sourceSize": {"w":400,"h":400}
},
{
	"filename": "walk003.png",
	"frame": {"x":2012,"y":3620,"w":400,"h":400},
	"rotated": false,
	"trimmed": false,
	"spriteSourceSize": {"x":0,"y":0,"w":400,"h":400},
	"sourceSize": {"w":400,"h":400}
},
{
	"filename": "walk004.png",
	"frame": {"x":2,"y":4022,"w":400,"h":400},
	"rotated": false,
	"trimmed": false,
	"spriteSourceSize": {"x":0,"y":0,"w":400,"h":400},
	"sourceSize": {"w":400,"h":400}
},
{
	"filename": "walk005.png",
	"frame": {"x":404,"y":4022,"w":400,"h":400},
	"rotated": false,
	"trimmed": false,
	"spriteSourceSize": {"x":0,"y":0,"w":400,"h":400},
	"sourceSize": {"w":400,"h":400}
},
{
	"filename": "walkslightangle001.png",
	"frame": {"x":806,"y":4022,"w":400,"h":400},
	"rotated": false,
	"trimmed": false,
	"spriteSourceSize": {"x":0,"y":0,"w":400,"h":400},
	"sourceSize": {"w":400,"h":400}
},
{
	"filename": "walkslightangle002.png",
	"frame": {"x":1208,"y":4022,"w":400,"h":400},
	"rotated": false,
	"trimmed": false,
	"spriteSourceSize": {"x":0,"y":0,"w":400,"h":400},
	"sourceSize": {"w":400,"h":400}
},
{
	"filename": "walkslightangle003.png",
	"frame": {"x":1610,"y":4022,"w":400,"h":400},
	"rotated": false,
	"trimmed": false,
	"spriteSourceSize": {"x":0,"y":0,"w":400,"h":400},
	"sourceSize": {"w":400,"h":400}
},
{
	"filename": "walkslightangle004.png",
	"frame": {"x":2012,"y":4022,"w":400,"h":400},
	"rotated": false,
	"trimmed": false,
	"spriteSourceSize": {"x":0,"y":0,"w":400,"h":400},
	"sourceSize": {"w":400,"h":400}
},
{
	"filename": "walkslightangle005.png",
	"frame": {"x":2,"y":4424,"w":400,"h":400},
	"rotated": false,
	"trimmed": false,
	"spriteSourceSize": {"x":0,"y":0,"w":400,"h":400},
	"sourceSize": {"w":400,"h":400}
},
{
	"filename": "walksteepangle001.png",
	"frame": {"x":404,"y":4424,"w":400,"h":400},
	"rotated": false,
	"trimmed": false,
	"spriteSourceSize": {"x":0,"y":0,"w":400,"h":400},
	"sourceSize": {"w":400,"h":400}
},
{
	"filename": "walksteepangle002.png",
	"frame": {"x":806,"y":4424,"w":400,"h":400},
	"rotated": false,
	"trimmed": false,
	"spriteSourceSize": {"x":0,"y":0,"w":400,"h":400},
	"sourceSize": {"w":400,"h":400}
},
{
	"filename": "walksteepangle003.png",
	"frame": {"x":1208,"y":4424,"w":400,"h":400},
	"rotated": false,
	"trimmed": false,
	"spriteSourceSize": {"x":0,"y":0,"w":400,"h":400},
	"sourceSize": {"w":400,"h":400}
}],
"meta": {
	"app": "http://www.codeandweb.com/texturepacker",
	"version": "1.0",
	"image": "slimegirl-animations.png",
	"format": "RGBA8888",
	"size": {"w":2414,"h":4826},
	"scale": "1",
	"smartupdate": "$TexturePacker:SmartUpdate:35e32652978069c920d24390ce77a273:7ad9f22362ff22add2ba9639973721e0:611f2116d0f1529c4c6e06abb852efd1$"
}
}
